<xlue>
	<control class="CoolJ.PanelOperateList">
		<attr_def>

		</attr_def>
		<method_def>

		</method_def>
		<event_def>

		</event_def>
		<objtemplate>
			<children>
				<obj id="bkg" class="TextureObject">
					<attr>
						<width>father.width</width>
						<height>father.height</height>
						<alpha>168</alpha>
					</attr></obj>

			</children>
			<eventlist>
				<event name="OnInitControl" file="PanelOperateList.xml.lua" func="OnInitControl" />
			</eventlist>
		</objtemplate>
	</control>
</xlue>